Workbook

Sheet Lifecycle_Overview
A1: Lifecycle Step | B1: Description | C1: Primary Owner | D1: Key Control Objective
A2: Trade Execution | B2: Trade is executed and captured in the trade booking system | C2: Front Office / Trading | D2: Ensure trade is accurately booked with correct economics
A3: Trade Validation | B3: Trade details are reviewed and validated by operations | C3: Middle Office / Operations | D3: Detect booking errors prior to settlement
A4: Settlement Instruction | B4: Settlement details are sent to custodian or clearing agent | C4: Operations | D4: Ensure correct settlement instructions and timing
A5: Cash Movement | B5: Cash is exchanged between counterparties upon settlement | C5: Custodian / Treasury | D5: Ensure cash moves in the correct amount and currency
A6: Reconciliation & Controls | B6: Expected trades and cash are reconciled against actual balances | C6: Operations / Control Team | D6: Identify breaks, fails, and unresolved differences
A7: Daily Batch Capacity | B7: Workbook supports up to 20 trades per processing cycle | C7: Operations | D7: Ensure controls scale with daily volume

Sheet Trade_Log
A1: Trade_ID | B1: Trade_Date | C1: Settle_Date | D1: Asset_Type | E1: Buy_Sell | F1: Quantity | G1: Price | H1: Trade_Amount | I1: Expected_Cash_Amount | J1: Currency | K1: Expected_Cash_Date
A2: T001 | B2: 46024 | C2: 46027 | D2: Equity | E2: BUY | F2: 100 | G2: 50 | H2: =F2*G2 -> 5000 | I2: =IF(E2="BUY",-H2,H2) -> -5000 | J2: USD | K2: =C2 -> 46027
A3: T002 | B3: 46024 | C3: 46027 | D3: Equity | E3: SELL | F3: 200 | G3: 25 | H3: =F3*G3 -> 5000 | I3: =IF(E3="BUY",-H3,H3) -> 5000 | J3: USD | K3: =C3 -> 46027
A4: T003 | B4: 46025 | C4: 46028 | D4: Bond | E4: BUY | F4: 10 | G4: 1000 | H4: =F4*G4 -> 10000 | I4: =IF(E4="BUY",-H4,H4) -> -10000 | J4: USD | K4: =C4 -> 46028
A5: T004 | B5: 46025 | C5: 46028 | D5: Equity | E5: SELL | F5: 150 | G5: 40 | H5: =F5*G5 -> 6000 | I5: =IF(E5="BUY",-H5,H5) -> 6000 | J5: USD | K5: =C5 -> 46028
A6: T005 | B6: 46026 | C6: 46029 | D6: Equity | E6: BUY | F6: 50 | G6: 60 | H6: =F6*G6 -> 3000 | I6: =IF(E6="BUY",-H6,H6) -> -3000 | J6: USD | K6: =C6 -> 46029
A7: T006 | B7: 46026 | C7: 46029 | D7: Bond | E7: SELL | F7: 5 | G7: 980 | H7: =F7*G7 -> 4900 | I7: =IF(E7="BUY",-H7,H7) -> 4900 | J7: USD | K7: =C7 -> 46029
H8: =F8*G8 -> 0 | I8: =IF(E8="BUY",-H8,H8) -> 0 | K8: =C8 -> 0
H9: =F9*G9 -> 0 | I9: =IF(E9="BUY",-H9,H9) -> 0 | K9: =C9 -> 0
H10: =F10*G10 -> 0 | I10: =IF(E10="BUY",-H10,H10) -> 0 | K10: =C10 -> 0
H11: =F11*G11 -> 0 | I11: =IF(E11="BUY",-H11,H11) -> 0 | K11: =C11 -> 0
H12: =F12*G12 -> 0 | I12: =IF(E12="BUY",-H12,H12) -> 0 | K12: =C12 -> 0
H13: =F13*G13 -> 0 | I13: =IF(E13="BUY",-H13,H13) -> 0 | K13: =C13 -> 0
H14: =F14*G14 -> 0 | I14: =IF(E14="BUY",-H14,H14) -> 0 | K14: =C14 -> 0
H15: =F15*G15 -> 0 | I15: =IF(E15="BUY",-H15,H15) -> 0 | K15: =C15 -> 0
H16: =F16*G16 -> 0 | I16: =IF(E16="BUY",-H16,H16) -> 0 | K16: =C16 -> 0
H17: =F17*G17 -> 0 | I17: =IF(E17="BUY",-H17,H17) -> 0 | K17: =C17 -> 0
H18: =F18*G18 -> 0 | I18: =IF(E18="BUY",-H18,H18) -> 0 | K18: =C18 -> 0
H19: =F19*G19 -> 0 | I19: =IF(E19="BUY",-H19,H19) -> 0 | K19: =C19 -> 0
... H21: =F21*G21 -> 0 | I21: =IF(E21="BUY",-H21,H21) -> 0 | K21: =C21 -> 0

Sheet Cash_Movements
A1: Cash_ID | B1: Transaction_Date | C1: Value_Date | D1: Asset_Type | E1: Signed_Cash_Amount | F1: Cash_Amount | G1: Currency | H1: Source | I1: Related_Trade_ID
A2: C001 | B2: 46027 | C2: 46027 | D2: Equity | E2: =F2 -> -5000 | F2: -5000 | G2: USD | H2: Custodian | I2: T001
A3: C002 | B3: 46027 | C3: 46027 | D3: Equity | E3: =F3 -> 5000 | F3: 5000 | G3: USD | H3: Custodian | I3: T002
A4: C003 | B4: 46029 | C4: 46029 | D4: Bond | E4: =F4 -> -10000 | F4: -10000 | G4: USD | H4: Custodian | I4: T003
A5: C004 | B5: 46028 | C5: 46028 | D5: Equity | E5: =F5 -> 5900 | F5: 5900 | G5: USD | H5: Custodian | I5: T004
A6: C005 | B6: 46029 | C6: 46029 | D6: Bond | E6: =F6 -> 4800 | F6: 4800 | G6: USD | H6: Custodian | I6: T006
E7: =F7 -> 0
E8: =F8 -> 0
E9: =F9 -> 0
E10: =F10 -> 0
E11: =F11 -> 0
E12: =F12 -> 0
E13: =F13 -> 0
E14: =F14 -> 0
E15: =F15 -> 0
E16: =F16 -> 0
E17: =F17 -> 0
E18: =F18 -> 0
... E21: =F21 -> 0

Sheet Cash_Reconciliation
A1: Trade_ID | B1: Asset_Type | C1: Currency | D1: Expected_Cash_Amount | E1: Expected_Cash_Date | F1: Actual_Cash_Amount | G1: Last_Value_Date | H1: Difference | I1: Status | J1: Break_Type
A2: {=_xlfn._xlws.FILTER(_xlfn.UNIQUE(Trade_Log!A2:A21),_xlfn.UNIQUE(Trade_Log!A2:A21)<>"")} -> T001 | B2: =IF($A2="","",_xlfn.XLOOKUP($A2,Trade_Log!$A:$A,Trade_Log!$D:$D,"")) -> Equity | C2: =IF($A2="","",_xlfn.XLOOKUP($A2,Trade_Log!$A:$A,Trade_Log!$J:$J,"")) -> USD | D2: =IFERROR(_xlfn.XLOOKUP($A2,Trade_Log!A:A,Trade_Log!I:I),0) -> -5000 | E2: =IF($A2="","",_xlfn.XLOOKUP($A2,Trade_Log!$A:$A,Trade_Log!$K:$K,"")) -> 46027 | F2: =SUMIF(Cash_Movements!$I:$I,$A2,Cash_Movements!$E:$E) -> -5000 | G2: =IF($A2="","",_xlfn.MAXIFS(Cash_Movements!$C:$C,Cash_Movements!$I:$I,$A2)) -> 46027 | H2: =D2-F2 -> 0 | I2: =IF($A2="","", IF($F2=0,"BREAK", IF($G2>$E2,"TIMING", IF(ROUND($H2,2)=0,"PASS","BREAK")))) -> PASS | J2: =IF($A2="","", IF($I2="PASS","", IF($I2="TIMING","Timing Difference", IF($F2=0,"Missing Cash","Amount Difference"))))
A3: T002 | B3: =IF($A3="","",_xlfn.XLOOKUP($A3,Trade_Log!$A:$A,Trade_Log!$D:$D,"")) -> Equity | C3: =IF($A3="","",_xlfn.XLOOKUP($A3,Trade_Log!$A:$A,Trade_Log!$J:$J,"")) -> USD | D3: =IFERROR(_xlfn.XLOOKUP($A3,Trade_Log!A:A,Trade_Log!I:I),0) -> 5000 | E3: =IF($A3="","",_xlfn.XLOOKUP($A3,Trade_Log!$A:$A,Trade_Log!$K:$K,"")) -> 46027 | F3: =SUMIF(Cash_Movements!$I:$I,$A3,Cash_Movements!$E:$E) -> 5000 | G3: =IF($A3="","",_xlfn.MAXIFS(Cash_Movements!$C:$C,Cash_Movements!$I:$I,$A3)) -> 46027 | H3: =D3-F3 -> 0 | I3: =IF($A3="","", IF($F3=0,"BREAK", IF($G3>$E3,"TIMING", IF(ROUND($H3,2)=0,"PASS","BREAK")))) -> PASS | J3: =IF($A3="","", IF($I3="PASS","", IF($I3="TIMING","Timing Difference", IF($F3=0,"Missing Cash","Amount Difference"))))
A4: T003 | B4: =IF($A4="","",_xlfn.XLOOKUP($A4,Trade_Log!$A:$A,Trade_Log!$D:$D,"")) -> Bond | C4: =IF($A4="","",_xlfn.XLOOKUP($A4,Trade_Log!$A:$A,Trade_Log!$J:$J,"")) -> USD | D4: =IFERROR(_xlfn.XLOOKUP($A4,Trade_Log!A:A,Trade_Log!I:I),0) -> -10000 | E4: =IF($A4="","",_xlfn.XLOOKUP($A4,Trade_Log!$A:$A,Trade_Log!$K:$K,"")) -> 46028 | F4: =SUMIF(Cash_Movements!$I:$I,$A4,Cash_Movements!$E:$E) -> -10000 | G4: =IF($A4="","",_xlfn.MAXIFS(Cash_Movements!$C:$C,Cash_Movements!$I:$I,$A4)) -> 46029 | H4: =D4-F4 -> 0 | I4: =IF($A4="","", IF($F4=0,"BREAK", IF($G4>$E4,"TIMING", IF(ROUND($H4,2)=0,"PASS","BREAK")))) -> TIMING | J4: =IF($A4="","", IF($I4="PASS","", IF($I4="TIMING","Timing Difference", IF($F4=0,"Missing Cash","Amount Difference")))) -> Timing Difference
A5: T004 | B5: =IF($A5="","",_xlfn.XLOOKUP($A5,Trade_Log!$A:$A,Trade_Log!$D:$D,"")) -> Equity | C5: =IF($A5="","",_xlfn.XLOOKUP($A5,Trade_Log!$A:$A,Trade_Log!$J:$J,"")) -> USD | D5: =IFERROR(_xlfn.XLOOKUP($A5,Trade_Log!A:A,Trade_Log!I:I),0) -> 6000 | E5: =IF($A5="","",_xlfn.XLOOKUP($A5,Trade_Log!$A:$A,Trade_Log!$K:$K,"")) -> 46028 | F5: =SUMIF(Cash_Movements!$I:$I,$A5,Cash_Movements!$E:$E) -> 5900 | G5: =IF($A5="","",_xlfn.MAXIFS(Cash_Movements!$C:$C,Cash_Movements!$I:$I,$A5)) -> 46028 | H5: =D5-F5 -> 100 | I5: =IF($A5="","", IF($F5=0,"BREAK", IF($G5>$E5,"TIMING", IF(ROUND($H5,2)=0,"PASS","BREAK")))) -> BREAK | J5: =IF($A5="","", IF($I5="PASS","", IF($I5="TIMING","Timing Difference", IF($F5=0,"Missing Cash","Amount Difference")))) -> Amount Difference
A6: T005 | B6: =IF($A6="","",_xlfn.XLOOKUP($A6,Trade_Log!$A:$A,Trade_Log!$D:$D,"")) -> Equity | C6: =IF($A6="","",_xlfn.XLOOKUP($A6,Trade_Log!$A:$A,Trade_Log!$J:$J,"")) -> USD | D6: =IFERROR(_xlfn.XLOOKUP($A6,Trade_Log!A:A,Trade_Log!I:I),0) -> -3000 | E6: =IF($A6="","",_xlfn.XLOOKUP($A6,Trade_Log!$A:$A,Trade_Log!$K:$K,"")) -> 46029 | F6: =SUMIF(Cash_Movements!$I:$I,$A6,Cash_Movements!$E:$E) -> 0 | G6: =IF($A6="","",_xlfn.MAXIFS(Cash_Movements!$C:$C,Cash_Movements!$I:$I,$A6)) -> 0 | H6: =D6-F6 -> -3000 | I6: =IF($A6="","", IF($F6=0,"BREAK", IF($G6>$E6,"TIMING", IF(ROUND($H6,2)=0,"PASS","BREAK")))) -> BREAK | J6: =IF($A6="","", IF($I6="PASS","", IF($I6="TIMING","Timing Difference", IF($F6=0,"Missing Cash","Amount Difference")))) -> Missing Cash
A7: T006 | B7: =IF($A7="","",_xlfn.XLOOKUP($A7,Trade_Log!$A:$A,Trade_Log!$D:$D,"")) -> Bond | C7: =IF($A7="","",_xlfn.XLOOKUP($A7,Trade_Log!$A:$A,Trade_Log!$J:$J,"")) -> USD | D7: =IFERROR(_xlfn.XLOOKUP($A7,Trade_Log!A:A,Trade_Log!I:I),0) -> 4900 | E7: =IF($A7="","",_xlfn.XLOOKUP($A7,Trade_Log!$A:$A,Trade_Log!$K:$K,"")) -> 46029 | F7: =SUMIF(Cash_Movements!$I:$I,$A7,Cash_Movements!$E:$E) -> 4800 | G7: =IF($A7="","",_xlfn.MAXIFS(Cash_Movements!$C:$C,Cash_Movements!$I:$I,$A7)) -> 46029 | H7: =D7-F7 -> 100 | I7: =IF($A7="","", IF($F7=0,"BREAK", IF($G7>$E7,"TIMING", IF(ROUND($H7,2)=0,"PASS","BREAK")))) -> BREAK | J7: =IF($A7="","", IF($I7="PASS","", IF($I7="TIMING","Timing Difference", IF($F7=0,"Missing Cash","Amount Difference")))) -> Amount Difference
B8: =IF($A8="","",_xlfn.XLOOKUP($A8,Trade_Log!$A:$A,Trade_Log!$D:$D,"")) | C8: =IF($A8="","",_xlfn.XLOOKUP($A8,Trade_Log!$A:$A,Trade_Log!$J:$J,"")) | D8: =IFERROR(_xlfn.XLOOKUP($A8,Trade_Log!A:A,Trade_Log!I:I),0) -> 0 | E8: =IF($A8="","",_xlfn.XLOOKUP($A8,Trade_Log!$A:$A,Trade_Log!$K:$K,"")) | F8: =SUMIF(Cash_Movements!$I:$I,$A8,Cash_Movements!$E:$E) -> 0 | G8: =IF($A8="","",_xlfn.MAXIFS(Cash_Movements!$C:$C,Cash_Movements!$I:$I,$A8)) | H8: =D8-F8 -> 0 | I8: =IF($A8="","", IF($F8=0,"BREAK", IF($G8>$E8,"TIMING", IF(ROUND($H8,2)=0,"PASS","BREAK")))) | J8: =IF($A8="","", IF($I8="PASS","", IF($I8="TIMING","Timing Difference", IF($F8=0,"Missing Cash","Amount Difference"))))
B9: =IF($A9="","",_xlfn.XLOOKUP($A9,Trade_Log!$A:$A,Trade_Log!$D:$D,"")) | C9: =IF($A9="","",_xlfn.XLOOKUP($A9,Trade_Log!$A:$A,Trade_Log!$J:$J,"")) | D9: =IFERROR(_xlfn.XLOOKUP($A9,Trade_Log!A:A,Trade_Log!I:I),0) -> 0 | E9: =IF($A9="","",_xlfn.XLOOKUP($A9,Trade_Log!$A:$A,Trade_Log!$K:$K,"")) | F9: =SUMIF(Cash_Movements!$I:$I,$A9,Cash_Movements!$E:$E) -> 0 | G9: =IF($A9="","",_xlfn.MAXIFS(Cash_Movements!$C:$C,Cash_Movements!$I:$I,$A9)) | H9: =D9-F9 -> 0 | I9: =IF($A9="","", IF($F9=0,"BREAK", IF($G9>$E9,"TIMING", IF(ROUND($H9,2)=0,"PASS","BREAK")))) | J9: =IF($A9="","", IF($I9="PASS","", IF($I9="TIMING","Timing Difference", IF($F9=0,"Missing Cash","Amount Difference"))))
B10: =IF($A10="","",_xlfn.XLOOKUP($A10,Trade_Log!$A:$A,Trade_Log!$D:$D,"")) | C10: =IF($A10="","",_xlfn.XLOOKUP($A10,Trade_Log!$A:$A,Trade_Log!$J:$J,"")) | D10: =IFERROR(_xlfn.XLOOKUP($A10,Trade_Log!A:A,Trade_Log!I:I),0) -> 0 | E10: =IF($A10="","",_xlfn.XLOOKUP($A10,Trade_Log!$A:$A,Trade_Log!$K:$K,"")) | F10: =SUMIF(Cash_Movements!$I:$I,$A10,Cash_Movements!$E:$E) -> 0 | G10: =IF($A10="","",_xlfn.MAXIFS(Cash_Movements!$C:$C,Cash_Movements!$I:$I,$A10)) | H10: =D10-F10 -> 0 | I10: =IF($A10="","", IF($F10=0,"BREAK", IF($G10>$E10,"TIMING", IF(ROUND($H10,2)=0,"PASS","BREAK")))) | J10: =IF($A10="","", IF($I10="PASS","", IF($I10="TIMING","Timing Difference", IF($F10=0,"Missing Cash","Amount Difference"))))
B11: =IF($A11="","",_xlfn.XLOOKUP($A11,Trade_Log!$A:$A,Trade_Log!$D:$D,"")) | C11: =IF($A11="","",_xlfn.XLOOKUP($A11,Trade_Log!$A:$A,Trade_Log!$J:$J,"")) | D11: =IFERROR(_xlfn.XLOOKUP($A11,Trade_Log!A:A,Trade_Log!I:I),0) -> 0 | E11: =IF($A11="","",_xlfn.XLOOKUP($A11,Trade_Log!$A:$A,Trade_Log!$K:$K,"")) | F11: =SUMIF(Cash_Movements!$I:$I,$A11,Cash_Movements!$E:$E) -> 0 | G11: =IF($A11="","",_xlfn.MAXIFS(Cash_Movements!$C:$C,Cash_Movements!$I:$I,$A11)) | H11: =D11-F11 -> 0 | I11: =IF($A11="","", IF($F11=0,"BREAK", IF($G11>$E11,"TIMING", IF(ROUND($H11,2)=0,"PASS","BREAK")))) | J11: =IF($A11="","", IF($I11="PASS","", IF($I11="TIMING","Timing Difference", IF($F11=0,"Missing Cash","Amount Difference"))))
B12: =IF($A12="","",_xlfn.XLOOKUP($A12,Trade_Log!$A:$A,Trade_Log!$D:$D,"")) | C12: =IF($A12="","",_xlfn.XLOOKUP($A12,Trade_Log!$A:$A,Trade_Log!$J:$J,"")) | D12: =IFERROR(_xlfn.XLOOKUP($A12,Trade_Log!A:A,Trade_Log!I:I),0) -> 0 | E12: =IF($A12="","",_xlfn.XLOOKUP($A12,Trade_Log!$A:$A,Trade_Log!$K:$K,"")) | F12: =SUMIF(Cash_Movements!$I:$I,$A12,Cash_Movements!$E:$E) -> 0 | G12: =IF($A12="","",_xlfn.MAXIFS(Cash_Movements!$C:$C,Cash_Movements!$I:$I,$A12)) | H12: =D12-F12 -> 0 | I12: =IF($A12="","", IF($F12=0,"BREAK", IF($G12>$E12,"TIMING", IF(ROUND($H12,2)=0,"PASS","BREAK")))) | J12: =IF($A12="","", IF($I12="PASS","", IF($I12="TIMING","Timing Difference", IF($F12=0,"Missing Cash","Amount Difference"))))
B13: =IF($A13="","",_xlfn.XLOOKUP($A13,Trade_Log!$A:$A,Trade_Log!$D:$D,"")) | C13: =IF($A13="","",_xlfn.XLOOKUP($A13,Trade_Log!$A:$A,Trade_Log!$J:$J,"")) | D13: =IFERROR(_xlfn.XLOOKUP($A13,Trade_Log!A:A,Trade_Log!I:I),0) -> 0 | E13: =IF($A13="","",_xlfn.XLOOKUP($A13,Trade_Log!$A:$A,Trade_Log!$K:$K,"")) | F13: =SUMIF(Cash_Movements!$I:$I,$A13,Cash_Movements!$E:$E) -> 0 | G13: =IF($A13="","",_xlfn.MAXIFS(Cash_Movements!$C:$C,Cash_Movements!$I:$I,$A13)) | H13: =D13-F13 -> 0 | I13: =IF($A13="","", IF($F13=0,"BREAK", IF($G13>$E13,"TIMING", IF(ROUND($H13,2)=0,"PASS","BREAK")))) | J13: =IF($A13="","", IF($I13="PASS","", IF($I13="TIMING","Timing Difference", IF($F13=0,"Missing Cash","Amount Difference"))))
B14: =IF($A14="","",_xlfn.XLOOKUP($A14,Trade_Log!$A:$A,Trade_Log!$D:$D,"")) | C14: =IF($A14="","",_xlfn.XLOOKUP($A14,Trade_Log!$A:$A,Trade_Log!$J:$J,"")) | D14: =IFERROR(_xlfn.XLOOKUP($A14,Trade_Log!A:A,Trade_Log!I:I),0) -> 0 | E14: =IF($A14="","",_xlfn.XLOOKUP($A14,Trade_Log!$A:$A,Trade_Log!$K:$K,"")) | F14: =SUMIF(Cash_Movements!$I:$I,$A14,Cash_Movements!$E:$E) -> 0 | G14: =IF($A14="","",_xlfn.MAXIFS(Cash_Movements!$C:$C,Cash_Movements!$I:$I,$A14)) | H14: =D14-F14 -> 0 | I14: =IF($A14="","", IF($F14=0,"BREAK", IF($G14>$E14,"TIMING", IF(ROUND($H14,2)=0,"PASS","BREAK")))) | J14: =IF($A14="","", IF($I14="PASS","", IF($I14="TIMING","Timing Difference", IF($F14=0,"Missing Cash","Amount Difference"))))
B15: =IF($A15="","",_xlfn.XLOOKUP($A15,Trade_Log!$A:$A,Trade_Log!$D:$D,"")) | C15: =IF($A15="","",_xlfn.XLOOKUP($A15,Trade_Log!$A:$A,Trade_Log!$J:$J,"")) | D15: =IFERROR(_xlfn.XLOOKUP($A15,Trade_Log!A:A,Trade_Log!I:I),0) -> 0 | E15: =IF($A15="","",_xlfn.XLOOKUP($A15,Trade_Log!$A:$A,Trade_Log!$K:$K,"")) | F15: =SUMIF(Cash_Movements!$I:$I,$A15,Cash_Movements!$E:$E) -> 0 | G15: =IF($A15="","",_xlfn.MAXIFS(Cash_Movements!$C:$C,Cash_Movements!$I:$I,$A15)) | H15: =D15-F15 -> 0 | I15: =IF($A15="","", IF($F15=0,"BREAK", IF($G15>$E15,"TIMING", IF(ROUND($H15,2)=0,"PASS","BREAK")))) | J15: =IF($A15="","", IF($I15="PASS","", IF($I15="TIMING","Timing Difference", IF($F15=0,"Missing Cash","Amount Difference"))))
B16: =IF($A16="","",_xlfn.XLOOKUP($A16,Trade_Log!$A:$A,Trade_Log!$D:$D,"")) | C16: =IF($A16="","",_xlfn.XLOOKUP($A16,Trade_Log!$A:$A,Trade_Log!$J:$J,"")) | D16: =IFERROR(_xlfn.XLOOKUP($A16,Trade_Log!A:A,Trade_Log!I:I),0) -> 0 | E16: =IF($A16="","",_xlfn.XLOOKUP($A16,Trade_Log!$A:$A,Trade_Log!$K:$K,"")) | F16: =SUMIF(Cash_Movements!$I:$I,$A16,Cash_Movements!$E:$E) -> 0 | G16: =IF($A16="","",_xlfn.MAXIFS(Cash_Movements!$C:$C,Cash_Movements!$I:$I,$A16)) | H16: =D16-F16 -> 0 | I16: =IF($A16="","", IF($F16=0,"BREAK", IF($G16>$E16,"TIMING", IF(ROUND($H16,2)=0,"PASS","BREAK")))) | J16: =IF($A16="","", IF($I16="PASS","", IF($I16="TIMING","Timing Difference", IF($F16=0,"Missing Cash","Amount Difference"))))
B17: =IF($A17="","",_xlfn.XLOOKUP($A17,Trade_Log!$A:$A,Trade_Log!$D:$D,"")) | C17: =IF($A17="","",_xlfn.XLOOKUP($A17,Trade_Log!$A:$A,Trade_Log!$J:$J,"")) | D17: =IFERROR(_xlfn.XLOOKUP($A17,Trade_Log!A:A,Trade_Log!I:I),0) -> 0 | E17: =IF($A17="","",_xlfn.XLOOKUP($A17,Trade_Log!$A:$A,Trade_Log!$K:$K,"")) | F17: =SUMIF(Cash_Movements!$I:$I,$A17,Cash_Movements!$E:$E) -> 0 | G17: =IF($A17="","",_xlfn.MAXIFS(Cash_Movements!$C:$C,Cash_Movements!$I:$I,$A17)) | H17: =D17-F17 -> 0 | I17: =IF($A17="","", IF($F17=0,"BREAK", IF($G17>$E17,"TIMING", IF(ROUND($H17,2)=0,"PASS","BREAK")))) | J17: =IF($A17="","", IF($I17="PASS","", IF($I17="TIMING","Timing Difference", IF($F17=0,"Missing Cash","Amount Difference"))))
B18: =IF($A18="","",_xlfn.XLOOKUP($A18,Trade_Log!$A:$A,Trade_Log!$D:$D,"")) | C18: =IF($A18="","",_xlfn.XLOOKUP($A18,Trade_Log!$A:$A,Trade_Log!$J:$J,"")) | D18: =IFERROR(_xlfn.XLOOKUP($A18,Trade_Log!A:A,Trade_Log!I:I),0) -> 0 | E18: =IF($A18="","",_xlfn.XLOOKUP($A18,Trade_Log!$A:$A,Trade_Log!$K:$K,"")) | F18: =SUMIF(Cash_Movements!$I:$I,$A18,Cash_Movements!$E:$E) -> 0 | G18: =IF($A18="","",_xlfn.MAXIFS(Cash_Movements!$C:$C,Cash_Movements!$I:$I,$A18)) | H18: =D18-F18 -> 0 | I18: =IF($A18="","", IF($F18=0,"BREAK", IF($G18>$E18,"TIMING", IF(ROUND($H18,2)=0,"PASS","BREAK")))) | J18: =IF($A18="","", IF($I18="PASS","", IF($I18="TIMING","Timing Difference", IF($F18=0,"Missing Cash","Amount Difference"))))
B19: =IF($A19="","",_xlfn.XLOOKUP($A19,Trade_Log!$A:$A,Trade_Log!$D:$D,"")) | C19: =IF($A19="","",_xlfn.XLOOKUP($A19,Trade_Log!$A:$A,Trade_Log!$J:$J,"")) | D19: =IFERROR(_xlfn.XLOOKUP($A19,Trade_Log!A:A,Trade_Log!I:I),0) -> 0 | E19: =IF($A19="","",_xlfn.XLOOKUP($A19,Trade_Log!$A:$A,Trade_Log!$K:$K,"")) | F19: =SUMIF(Cash_Movements!$I:$I,$A19,Cash_Movements!$E:$E) -> 0 | G19: =IF($A19="","",_xlfn.MAXIFS(Cash_Movements!$C:$C,Cash_Movements!$I:$I,$A19)) | H19: =D19-F19 -> 0 | I19: =IF($A19="","", IF($F19=0,"BREAK", IF($G19>$E19,"TIMING", IF(ROUND($H19,2)=0,"PASS","BREAK")))) | J19: =IF($A19="","", IF($I19="PASS","", IF($I19="TIMING","Timing Difference", IF($F19=0,"Missing Cash","Amount Difference"))))
... B21: =IF($A21="","",_xlfn.XLOOKUP($A21,Trade_Log!$A:$A,Trade_Log!$D:$D,"")) | C21: =IF($A21="","",_xlfn.XLOOKUP($A21,Trade_Log!$A:$A,Trade_Log!$J:$J,"")) | D21: =IFERROR(_xlfn.XLOOKUP($A21,Trade_Log!A:A,Trade_Log!I:I),0) -> 0 | E21: =IF($A21="","",_xlfn.XLOOKUP($A21,Trade_Log!$A:$A,Trade_Log!$K:$K,"")) | F21: =SUMIF(Cash_Movements!$I:$I,$A21,Cash_Movements!$E:$E) -> 0 | G21: =IF($A21="","",_xlfn.MAXIFS(Cash_Movements!$C:$C,Cash_Movements!$I:$I,$A21)) | H21: =D21-F21 -> 0 | I21: =IF($A21="","", IF($F21=0,"BREAK", IF($G21>$E21,"TIMING", IF(ROUND($H21,2)=0,"PASS","BREAK")))) | J21: =IF($A21="","", IF($I21="PASS","", IF($I21="TIMING","Timing Difference", IF($F21=0,"Missing Cash","Amount Difference"))))

Sheet Control_Summary
A1: Control_Date | B1: Total_Trades | C1: Total_Cash_Movements | D1: Unreconciled_Trades | E1: Total_Cash_Difference | F1: Overall_Status
A2: =TODAY() -> 46050 | B2: =COUNTA(Trade_Log!A2:A21) -> 6 | C2: =COUNTA(Cash_Movements!A2:A21) -> 5 | D2: =COUNTIF(Cash_Reconciliation!I2:I21,"TIMING")+COUNTIF(Cash_Reconciliation!I2:I21,"BREAK") -> 4 | E2: {=SUMPRODUCT(ABS(Cash_Reconciliation!H2:H21)*(Cash_Reconciliation!I2:I21<>"PASS"))} -> 3200 | F2: =IF(COUNTIF(Cash_Reconciliation!I2:I21,"BREAK")>0,"Red", IF(COUNTIF(Cash_Reconciliation!I2:I21,"TIMING")>0,"Amber","Green")) -> Red
